apex_markets/__init__.py
apex_markets-0.0.6.dist-info/METADATA
apex_markets-0.0.6.dist-info/WHEEL
apex_markets-0.0.6.dist-info/top_level.txt
apex_markets-0.0.6.dist-info/RECORD
