Metadata-Version: 2.1
Name: apex-markets
Version: 0.0.6
Summary: UNKNOWN
Home-page: UNKNOWN
Author: Apex Markets
Author-email: ljwcharles@gmail.com
License: UNKNOWN
Keywords: apex python client
Platform: UNKNOWN
Classifier: Programming Language :: Python :: 3
Classifier: License :: OSI Approved :: MIT License
Classifier: Operating System :: OS Independent
Requires-Dist: requests
Requires-Dist: pandas
Requires-Dist: numpy
Requires-Dist: matplotlib
